21-10/add-shift.v
`timescale 1ns / 1ps

module add_shft_mul (
                     input         clk,
                     input         rst,
                     
                     input signed [7:0]   a, 
                     input signed [7:0]   b,
                     output reg signed [15:0] c,
                     input         start,
                     output        done
                     );

   reg [3:0]                     counter;
  

   assign done = (counter == 4'd8);

   always@(posedge clk)
     if(rst)
       counter <= 4'd0;
     else if (start) begin
       counter <= 4'd0;
       
     end
     else if (counter != 4'd8)
       counter <= counter + 1'b1;
   
   
     always@(posedge clk)
     if(rst)
       c <= 16'd0;
     else if(counter != 4'd8) begin 
        c <= (c>>1) + (b[counter]? a<<7: 16'd0);
     end
     else if(counter == 4'd8)begin
        c <= (c>>1) - (b[counter]? a<<7: 16'd0);
     end


endmodule


module add_shft_mul_tb ();

   reg clk, rst;
   reg signed [7:0] a, b;
   wire signed [15:0] c;
   reg         start;
   wire        done;
   
   add_shft_mul mult0 (
                       .clk(clk),
                       .rst(rst),
                     
                       .a(a), 
                       .b(b),
                       .c(c),
                       .start(start),
                       .done(done)
                     );   

   initial begin

      $dumpfile("dump.vcd");
      $dumpvars;
      
      rst = 1;
      clk = 1;
      start = 0;

      a=10;
      b = -65;

      @(posedge clk) #1 rst=0;

      #5 @(posedge clk) #1 start=1;
      @(posedge clk) #1 start=0;

      @(posedge done) $display("%d", c);
      
      @(posedge clk) $finish;
   end
   
   always #10 clk = ~clk;
 
endmodule

21-10/dump.vcd
$date
	Mon Oct 28 16:09:13 2019
$end
$version
	Icarus Verilog
$end
$timescale
	1ps
$end
$scope module add_shft_mul_tb $end
$var wire 1 ! done $end
$var wire 16 " c [15:0] $end
$var reg 8 # a [7:0] $end
$var reg 8 $ b [7:0] $end
$var reg 1 % clk $end
$var reg 1 & rst $end
$var reg 1 ' start $end
$scope module mult0 $end
$var wire 8 ( a [7:0] $end
$var wire 8 ) b [7:0] $end
$var wire 1 % clk $end
$var wire 1 & rst $end
$var wire 1 ' start $end
$var wire 1 ! done $end
$var reg 16 * c [15:0] $end
$var reg 4 + counter [3:0] $end
$upscope $end
$upscope $end
$enddefinitions $end
#0
$dumpvars
b0 +
b0 *
b10111111 )
b1010 (
0'
1&
1%
b10111111 $
b1010 #
b0 "
0!
$end
#10000
0%
#20000
1%
#21000
0&
#30000
0%
#40000
b1 +
b10100000000 "
b10100000000 *
1%
#41000
1'
#50000
0%
#60000
b11110000000 "
b11110000000 *
b0 +
1%
#61000
0'
#70000
0%
#80000
b1 +
b100011000000 "
b100011000000 *
1%
#90000
0%
#100000
b100101100000 "
b100101100000 *
b10 +
1%
#110000
0%
#120000
b11 +
b100110110000 "
b100110110000 *
1%
#130000
0%
#140000
b100111011000 "
b100111011000 *
b100 +
1%
#150000
0%
#160000
b101 +
b100111101100 "
b100111101100 *
1%
#170000
0%
#180000
b100111110110 "
b100111110110 *
b110 +
1%
#190000
0%
#200000
b111 +
b10011111011 "
b10011111011 *
1%
#210000
0%
#220000
b11101111101 "
b11101111101 *
1!
b1000 +
1%
#230000
0%
#240000
bx "
bx *
1%
