Test_1/3/program.v
//y(n) = 0.25*y(n-1)+0.5*x(n).

module test_ex3 (
                  input clk,
                  input [4:0] x,
                  input xval,
                  input rst,
                  output reg [4:0] y,
                  output reg yval
                  );

   reg signed [4:0] ym1;

   always @(posedge clk) begin 
        if (rst) begin
            y <= 0;
            ym1 <= 0;
            yval <=0;
        end
        else if(xval) begin
            ym1 <= y;
            yval <=0;
        end
        else begin
            //y<= ym1 >> 2 + x >> 1; //would result in Q2 + Q1 and loss of data
            y <= ym1 + x >> 1; //output must be Q2 so ym2 doesent need to be shifted, x must be shifted once to the right in order to be in the same q as y
            yval <=1 ;
        end



   end

endmodule

Test_1/3/program_tb.v

module programtb ();

   reg clk, rst;
   reg [3:0] X;
   reg         start;
   wire        done;
   wire [4:0] Y;
           
   
   test_ex3 uut (
                       .clk(clk),
                       .rst(rst),
                     
                       .xval(start), 
                       .x(X),
                       .y(Y),
                       .yval(done)
                     );   

   initial begin

      $dumpfile("dump.vcd");
      $dumpvars;
      
      rst = 1;
      clk = 1;
      start = 0;

      X = 2;

      @(posedge clk) #1 rst=0;

      #5 @(posedge clk) #1 start=1;
      @(posedge clk) #1 start=0;
      
      //@(posedge clk) $finish;

      #500

      X = 3;

      #5 @(posedge clk) #1 start=1;
      @(posedge clk) #1 start=0;
      #500

      $finish;
   end
   
   always #10 clk = ~clk;
 
endmodule

Test_1/3/dump.vcd
$date
	Thu Nov 21 14:13:38 2019
$end
$version
	Icarus Verilog
$end
$timescale
	1s
$end
$scope module programtb $end
$var wire 1 ! done $end
$var wire 5 " Y [4:0] $end
$var reg 4 # X [3:0] $end
$var reg 1 $ clk $end
$var reg 1 % rst $end
$var reg 1 & start $end
$scope module uut $end
$var wire 1 $ clk $end
$var wire 1 % rst $end
$var wire 5 ' x [4:0] $end
$var wire 1 & xval $end
$var reg 5 ( y [4:0] $end
$var reg 5 ) ym1 [4:0] $end
$var reg 1 ! yval $end
$upscope $end
$upscope $end
$enddefinitions $end
#0
$dumpvars
b0 )
b0 (
b10 '
0&
1%
1$
b10 #
b0 "
0!
$end
#10
0$
#20
1$
#21
0%
#30
0$
#40
1!
b1 "
b1 (
1$
#41
1&
#50
0$
#60
0!
b1 )
1$
#61
0&
#70
0$
#80
1!
1$
#90
0$
#100
1$
#110
0$
#120
1$
#130
0$
#140
1$
#150
0$
#160
1$
#170
0$
#180
1$
#190
0$
#200
1$
#210
0$
#220
1$
#230
0$
#240
1$
#250
0$
#260
1$
#270
0$
#280
1$
#290
0$
#300
1$
#310
0$
#320
1$
#330
0$
#340
1$
#350
0$
#360
1$
#370
0$
#380
1$
#390
0$
#400
1$
#410
0$
#420
1$
#430
0$
#440
1$
#450
0$
#460
1$
#470
0$
#480
1$
#490
0$
#500
1$
#510
0$
#520
1$
#530
0$
#540
1$
#550
0$
#560
1$
#561
b11 '
b11 #
#570
0$
#580
b10 "
b10 (
1$
#581
1&
#590
0$
#600
0!
b10 )
1$
#601
0&
#610
0$
#620
1!
1$
